{"/*":["X-Frame-Options: DENY","X-XSS-Protection: 1; mode=block","X-Content-Type-Options: nosniff","Referrer-Policy: same-origin"],"/styles.61be66dbfda9a5d01ded.css":["Cache-Control: public, max-age=31536000, immutable"],"/commons-10534aae502d5bb79703.js":["Cache-Control: public, max-age=31536000, immutable"],"/component---cache-plasmic-components-pages-index-jsx-57a34e4e7854192c3b34.js":["Cache-Control: public, max-age=31536000, immutable"],"/component---cache-plasmic-components-pages-post-jsx-86299d6cf08831330a32.js":["Cache-Control: public, max-age=31536000, immutable"],"/webpack-runtime-6438cc9851fbcccf817c.js":["Cache-Control: public, max-age=31536000, immutable"],"/framework-e886f61ee3e03a6355e5.js":["Cache-Control: public, max-age=31536000, immutable"],"/app-4a694dec06d00825c738.js":["Cache-Control: public, max-age=31536000, immutable"],"/static/*":["Cache-Control: public, max-age=31536000, immutable"],"/sw.js":["Cache-Control: public, max-age=0, must-revalidate"],"/":["Link: </webpack-runtime-6438cc9851fbcccf817c.js>; rel=preload; as=script; nopush","Link: </framework-e886f61ee3e03a6355e5.js>; rel=preload; as=script; nopush","Link: </app-4a694dec06d00825c738.js>; rel=preload; as=script; nopush","Link: </commons-10534aae502d5bb79703.js>; rel=preload; as=script; nopush","Link: </component---cache-plasmic-components-pages-index-jsx-57a34e4e7854192c3b34.js>; rel=preload; as=script; nopush","Link: </page-data/app-data.json>; rel=preload; as=fetch; crossorigin; nopush","Link: </page-data/index/page-data.json>; rel=preload; as=fetch; crossorigin; nopush"],"/post":["Link: </webpack-runtime-6438cc9851fbcccf817c.js>; rel=preload; as=script; nopush","Link: </framework-e886f61ee3e03a6355e5.js>; rel=preload; as=script; nopush","Link: </app-4a694dec06d00825c738.js>; rel=preload; as=script; nopush","Link: </commons-10534aae502d5bb79703.js>; rel=preload; as=script; nopush","Link: </component---cache-plasmic-components-pages-post-jsx-86299d6cf08831330a32.js>; rel=preload; as=script; nopush","Link: </page-data/app-data.json>; rel=preload; as=fetch; crossorigin; nopush","Link: </page-data/post/page-data.json>; rel=preload; as=fetch; crossorigin; nopush"]}